D3JsRumenjiaochengV10/README.md
D3JsRumenjiaochengV10/__init__.py
D3JsRumenjiaochengV10/__main__.py
D3JsRumenjiaochengV10/file.epub
D3JsRumenjiaochengV10/index.html
D3JsRumenjiaochengV10/css/__init__.py
D3JsRumenjiaochengV10/css/annotations.css
D3JsRumenjiaochengV10/css/main.css
D3JsRumenjiaochengV10/css/normalize.css
D3JsRumenjiaochengV10/css/popup.css
D3JsRumenjiaochengV10/font/__init__.py
D3JsRumenjiaochengV10/font/fontello.eot
D3JsRumenjiaochengV10/font/fontello.svg
D3JsRumenjiaochengV10/font/fontello.ttf
D3JsRumenjiaochengV10/font/fontello.woff
D3JsRumenjiaochengV10/img/__init__.py
D3JsRumenjiaochengV10/img/annotator-glyph-sprite.png
D3JsRumenjiaochengV10/img/annotator-icon-sprite.png
D3JsRumenjiaochengV10/img/apple-touch-icon.png
D3JsRumenjiaochengV10/img/cancelfullscreen.png
D3JsRumenjiaochengV10/img/close.png
D3JsRumenjiaochengV10/img/fullscreen.png
D3JsRumenjiaochengV10/img/loader.gif
D3JsRumenjiaochengV10/img/menu-icon.png
D3JsRumenjiaochengV10/img/save.png
D3JsRumenjiaochengV10/img/saved.png
D3JsRumenjiaochengV10/img/settings-s.png
D3JsRumenjiaochengV10/img/settings.png
D3JsRumenjiaochengV10/img/star.png
D3JsRumenjiaochengV10/js/__init__.py
D3JsRumenjiaochengV10/js/epub.js
D3JsRumenjiaochengV10/js/epub.min.js
D3JsRumenjiaochengV10/js/epub.min.map
D3JsRumenjiaochengV10/js/hooks.min.js
D3JsRumenjiaochengV10/js/hooks.min.map
D3JsRumenjiaochengV10/js/reader.js
D3JsRumenjiaochengV10/js/reader.js.map
D3JsRumenjiaochengV10/js/reader.min.js
D3JsRumenjiaochengV10/js/reader.min.map
D3JsRumenjiaochengV10/js/hooks/__init__.py
D3JsRumenjiaochengV10/js/hooks/extensions/__init__.py
D3JsRumenjiaochengV10/js/hooks/extensions/highlight.js
D3JsRumenjiaochengV10/js/libs/__init__.py
D3JsRumenjiaochengV10/js/libs/jquery.min.js
D3JsRumenjiaochengV10/js/libs/localforage.min.js
D3JsRumenjiaochengV10/js/libs/screenfull.js
D3JsRumenjiaochengV10/js/libs/screenfull.min.js
D3JsRumenjiaochengV10/js/libs/zip.min.js
D3JsRumenjiaochengV10/js/plugins/__init__.py
d3_js_rumenjiaocheng_v1_0-2024.3.2.0.dist-info/METADATA
d3_js_rumenjiaocheng_v1_0-2024.3.2.0.dist-info/WHEEL
d3_js_rumenjiaocheng_v1_0-2024.3.2.0.dist-info/entry_points.txt
d3_js_rumenjiaocheng_v1_0-2024.3.2.0.dist-info/top_level.txt
d3_js_rumenjiaocheng_v1_0-2024.3.2.0.dist-info/RECORD
